corels/__init__.py
corels/_corels.cpython-37m-darwin.so
corels/corels.py
corels/utils.py
corels-1.1.28.dist-info/LICENSE
corels-1.1.28.dist-info/METADATA
corels-1.1.28.dist-info/WHEEL
corels-1.1.28.dist-info/top_level.txt
corels-1.1.28.dist-info/RECORD
