Metadata-Version: 2.1
Name: corels
Version: 1.1.28
Summary: Python binding of the CORELS algorithm
Home-page: https://github.com/fingoldin/pycorels
Author: Elaine Angelino, Nicholas Larus-Stone, Hongyu Yang, Cythnia Rudin, Vassilios Kaxiras, Margo Seltzer
Author-email: vassilioskaxiras@gmail.com
License: UNKNOWN
Platform: UNKNOWN
Classifier: Programming Language :: C++
Classifier: License :: OSI Approved :: GNU General Public License v3 (GPLv3)
Classifier: Operating System :: OS Independent
Requires-Python: >=2.7
Requires-Dist: numpy
